pyfahrplan/__init__.py
pyfahrplan/config.py
pyfahrplan/fahrplan_cache.sqlite
pyfahrplan/fahrplan_cache2.sqlite
pyfahrplan/lib.py
pyfahrplan/pyfahrplan_cli.py
pyfahrplan-1.1.0.dist-info/entry_points.txt
pyfahrplan-1.1.0.dist-info/LICENSE
pyfahrplan-1.1.0.dist-info/WHEEL
pyfahrplan-1.1.0.dist-info/METADATA
pyfahrplan-1.1.0.dist-info/RECORD
