Metadata-Version: 2.1
Name: pyfahrplan
Version: 1.1.0
Summary: A CCC Fahrplan CLI
Home-page: https://github.com/saschalalala/pyfahrplan
License: MIT
Keywords: cli,ccc,calendar,console
Author: Sascha
Author-email: saschalalala@github.com
Requires-Python: >=3.8,<4.0
Classifier: License :: OSI Approved :: MIT License
Classifier: Programming Language :: Python :: 3
Classifier: Programming Language :: Python :: 3.10
Classifier: Programming Language :: Python :: 3.8
Classifier: Programming Language :: Python :: 3.9
Requires-Dist: click (>=8.0,<9.0)
Requires-Dist: python-dateutil (>=2.8.1,<3.0.0)
Requires-Dist: requests (>=2.26.0,<3.0.0)
Requires-Dist: requests_cache (>=0.8.1,<0.9.0)
Requires-Dist: rich (>=10.16.1,<11.0.0)
Project-URL: Repository, https://github.com/saschalalala/pyfahrplan
